pm4pydistr/__init__.py
pm4pydistr/configuration.py
pm4pydistr/local_wrapper/__init__.py
pm4pydistr/local_wrapper/distr_log_obj.py
pm4pydistr/local_wrapper/factory.py
pm4pydistr/local_wrapper/versions/__init__.py
pm4pydistr/local_wrapper/versions/classic.py
pm4pydistr/log_handlers/__init__.py
pm4pydistr/log_handlers/parquet.py
pm4pydistr/log_handlers/parquet_filtering/__init__.py
pm4pydistr/log_handlers/parquet_filtering/factory.py
pm4pydistr/log_handlers/parquet_filtering/versions/__init__.py
pm4pydistr/log_handlers/parquet_filtering/versions/attributes_neg_events.py
pm4pydistr/log_handlers/parquet_filtering/versions/attributes_neg_trace.py
pm4pydistr/log_handlers/parquet_filtering/versions/attributes_pos_events.py
pm4pydistr/log_handlers/parquet_filtering/versions/attributes_pos_trace.py
pm4pydistr/log_handlers/parquet_filtering/versions/case_performance_filter.py
pm4pydistr/log_handlers/parquet_filtering/versions/end_activities.py
pm4pydistr/log_handlers/parquet_filtering/versions/ltl.py
pm4pydistr/log_handlers/parquet_filtering/versions/numeric_attr_events.py
pm4pydistr/log_handlers/parquet_filtering/versions/numeric_attr_traces.py
pm4pydistr/log_handlers/parquet_filtering/versions/paths_neg_trace.py
pm4pydistr/log_handlers/parquet_filtering/versions/paths_pos_trace.py
pm4pydistr/log_handlers/parquet_filtering/versions/start_activities.py
pm4pydistr/log_handlers/parquet_filtering/versions/timestamp_events.py
pm4pydistr/log_handlers/parquet_filtering/versions/timestamp_trace_containing.py
pm4pydistr/log_handlers/parquet_filtering/versions/timestamp_trace_intersecting.py
pm4pydistr/log_handlers/parquet_filtering/versions/variants.py
pm4pydistr/master/__init__.py
pm4pydistr/master/db_manager.py
pm4pydistr/master/master.py
pm4pydistr/master/master_service.py
pm4pydistr/master/session_checker.py
pm4pydistr/master/variable_container.py
pm4pydistr/master/rqsts/__init__.py
pm4pydistr/master/rqsts/attr_names_req.py
pm4pydistr/master/rqsts/attr_values_req.py
pm4pydistr-0.1.55.dist-info/LICENSE
pm4pydistr-0.1.55.dist-info/METADATA
pm4pydistr-0.1.55.dist-info/WHEEL
pm4pydistr-0.1.55.dist-info/top_level.txt
pm4pydistr-0.1.55.dist-info/RECORD
