Metadata-Version: 2.1
Name: pm4pydistr
Version: 0.1.55
Summary: Support for distributed logs and computations in PM4Py
Home-page: http://www.pm4py.org
Author: PADS
Author-email: pm4py@pads.rwth-aachen.de
License: GPL 3.0
Project-URL: Documentation, http://pm4py.pads.rwth-aachen.de/documentation/
Project-URL: Source, https://github.com/pm4py/pm4py-distr
Project-URL: Tracker, https://github.com/pm4py/pm4py-distr/issues
Platform: UNKNOWN
License-File: LICENSE
Requires-Dist: pm4py (>=2.2.18)
Requires-Dist: requests
Requires-Dist: Flask
Requires-Dist: flask-cors
Requires-Dist: psutil
Requires-Dist: pyarrow (>=6.0.0)
Requires-Dist: pm4pycvxopt (>=0.0.11)
